tgc/__init__.py
tgc/convert_export.py
tgc/convert_media_types.py
tgc/tg-blog.html
tgc/pyro/__init__.py
tgc/pyro/__main__.py
tgc/pyro/config.py
tgc/pyro/consts.py
tgc/pyro/convert.py
tgc/pyro/crawl.py
tgc/pyro/download_media.py
tgc/pyro/grouper.py
tgc/rss/__main__.py
tgc/rss/posts_to_feed.py
tgc-1.1.1.dist-info/LICENSE
tgc-1.1.1.dist-info/METADATA
tgc-1.1.1.dist-info/WHEEL
tgc-1.1.1.dist-info/entry_points.txt
tgc-1.1.1.dist-info/top_level.txt
tgc-1.1.1.dist-info/RECORD
