Metadata-Version: 2.1
Name: tgc
Version: 1.1.1
Summary: Telegram Channel Backup Crawler
Author-email: Azalea Gui <me@hydev.org>
License: MIT License
Project-URL: Homepage, https://github.com/one-among-us/TelegramBackup
Keywords: telegram,backup
Classifier: Programming Language :: Python :: 3
Requires-Python: >=3.10
License-File: LICENSE
Requires-Dist: toml ~=0.10.2
Requires-Dist: pyrogram ~=2.0.100
Requires-Dist: tgcrypto ~=1.2.5
Requires-Dist: requests ~=2.28.2
Requires-Dist: hypy-utils >=1.0.17
Requires-Dist: pillow ~=9.4.0
Requires-Dist: feedgen ~=0.9.0
Requires-Dist: markdown ~=3.4.1
Requires-Dist: importlib-metadata ~=6.0.0
